pyfftc/__init__.py
pyfftc/pyfftc.py
pyfftc/test_pyfftc.py
pyfftc-1.2.dist-info/METADATA
pyfftc-1.2.dist-info/WHEEL
pyfftc-1.2.dist-info/top_level.txt
pyfftc-1.2.dist-info/RECORD
