Metadata-Version: 2.1
Name: pyfftc
Version: 1.2
Summary: UNKNOWN
Home-page: UNKNOWN
Author: ['Michael Kellman']
Author-email: michael.kellman@ucsf.edu
License: BSD
Platform: UNKNOWN
Requires-Dist: torch (>=1.7.0)
